Juwel_2/Formatted_expiration_finder.py
Juwel_2/GUI_element_finder.py
Juwel_2/Main.py
Juwel_2/Widget_index_finder.py
Juwel_2/__init__.py
Juwel_2/text_parser.py
Juwell-2.1.16.dist-info/METADATA
Juwell-2.1.16.dist-info/WHEEL
Juwell-2.1.16.dist-info/entry_points.txt
Juwell-2.1.16.dist-info/top_level.txt
Juwell-2.1.16.dist-info/RECORD
